cdds_demo_may/__init__.py
cdds_demo_may/cdds_demo_may.py
cdds_demo_may-0.1.1.dist-info/AUTHORS.rst
cdds_demo_may-0.1.1.dist-info/LICENSE
cdds_demo_may-0.1.1.dist-info/METADATA
cdds_demo_may-0.1.1.dist-info/WHEEL
cdds_demo_may-0.1.1.dist-info/top_level.txt
cdds_demo_may-0.1.1.dist-info/RECORD
