Metadata-Version: 2.1
Name: cdds-demo-may
Version: 0.1.1
Summary: Quick demo package
Home-page: https://github.com/jirvingphd/cdds_demo_may
Author: James Irving
Author-email: jirving@codingdojo.com
License: GNU General Public License v3
Keywords: cdds_demo_may
Classifier: Development Status :: 2 - Pre-Alpha
Classifier: Intended Audience :: Developers
Classifier: License :: OSI Approved :: GNU General Public License v3 (GPLv3)
Classifier: Natural Language :: English
Classifier: Programming Language :: Python :: 3
Classifier: Programming Language :: Python :: 3.6
Classifier: Programming Language :: Python :: 3.7
Classifier: Programming Language :: Python :: 3.8
Requires-Python: >=3.6
License-File: LICENSE
License-File: AUTHORS.rst
